pyvad/__init__.py
pyvad/effects.py
pyvad/vad.py
pyvad-0.2.0.dist-info/WHEEL
pyvad-0.2.0.dist-info/METADATA
pyvad-0.2.0.dist-info/RECORD
