Metadata-Version: 2.1
Name: pyvad
Version: 0.2.0
Summary: 'py-webrtcvad wrapper for trimming speech clips'
Home-page: https://github.com/F-Tag/python-vad
License: MIT
Author: Fumiaki Taguchi
Requires-Python: >=3.8,<4.0
Classifier: Development Status :: 4 - Beta
Classifier: License :: OSI Approved :: MIT License
Classifier: Operating System :: OS Independent
Classifier: Programming Language :: Python :: 3
Classifier: Programming Language :: Python :: 3.10
Classifier: Programming Language :: Python :: 3.8
Classifier: Programming Language :: Python :: 3.9
Classifier: Topic :: Multimedia :: Sound/Audio
Classifier: Topic :: Multimedia :: Sound/Audio :: Analysis
Classifier: Topic :: Multimedia :: Sound/Audio :: Speech
Classifier: Topic :: Scientific/Engineering :: Human Machine Interfaces
Classifier: Topic :: Scientific/Engineering :: Information Analysis
Requires-Dist: librosa (>=0.9.2,<0.10.0)
Requires-Dist: numpy (>=1.23.0,<2.0.0)
Requires-Dist: webrtcvad (>=2.0.10,<3.0.0)
Project-URL: Repository, https://github.com/F-Tag/python-vad
